copyifc/__init__.py
copyifc/copyifc.py
copyifc-0.1.1.dist-info/LICENSE
copyifc-0.1.1.dist-info/WHEEL
copyifc-0.1.1.dist-info/METADATA
copyifc-0.1.1.dist-info/RECORD
