Metadata-Version: 2.1
Name: copyifc
Version: 0.1.1
Summary: Author:     LanHao
Home-page: https://github.com/bigpangl/copyifc
Author: LHao
Author-email: bigpangl@163.com
Classifier: License :: OSI Approved :: MIT License
